firesong/Evolution.py
firesong/Firesong.py
firesong/FluxPDF.py
firesong/Legend.py
firesong/Luminosity.py
firesong/__init__.py
firesong/distance.py
firesong/input_output.py
firesong/sampling.py
firesong-1.8.dist-info/AUTHORS.md
firesong-1.8.dist-info/LICENSE
firesong-1.8.dist-info/METADATA
firesong-1.8.dist-info/WHEEL
firesong-1.8.dist-info/top_level.txt
firesong-1.8.dist-info/RECORD
